{"meta":{"type":"db","canSave":true,"canEdit":true,"canAdmin":true,"canStar":true,"canDelete":true,"slug":"kt-cloud-lb-dashboard-ktcloud-test-dx-m1","url":"/d/ktcloud-lb-account1-complete/kt-cloud-lb-dashboard-ktcloud-test-dx-m1","expires":"0001-01-01T00:00:00Z","created":"2025-07-12T09:17:36Z","updated":"2025-07-12T09:17:36Z","updatedBy":"admin","createdBy":"admin","version":1,"hasAcl":false,"isFolder":false,"apiVersion":"v0alpha1","folderId":0,"folderUid":"","folderTitle":"General","folderUrl":"","provisioned":false,"provisionedExternalId":"","annotationsPermissions":{"dashboard":{"canAdd":true,"canEdit":true,"canDelete":true},"organization":{"canAdd":true,"canEdit":true,"canDelete":true}}},"dashboard":{"__inputs":[{"description":"","label":"Prometheus","name":"ktc_PROMETHEUS","pluginId":"prometheus","pluginName":"Prometheus","type":"datasource"}],"__requires":[{"id":"stat","name":"Stat","type":"panel","version":""},{"id":"timeseries","name":"Time series","type":"panel","version":""},{"id":"table","name":"Table","type":"panel","version":""},{"id":"piechart","name":"Pie chart","type":"panel","version":""},{"id":"grafana","name":"Grafana","type":"grafana","version":"11.4.0"},{"id":"prometheus","name":"Prometheus","type":"datasource","version":"3.1.0"}],"annotations":{"list":[{"builtIn":1,"datasource":{"type":"grafana","uid":"-- Grafana --"},"enable":true,"hide":true,"iconColor":"rgba(0, 211, 255, 1)","name":"Annotations \u0026 Alerts","type":"dashboard"}]},"editable":true,"fiscalYearStartMonth":0,"graphTooltip":0,"id":129,"links":[],"panels":[{"collapsed":false,"gridPos":{"h":1,"w":24,"x":0,"y":0},"id":1,"panels":[],"title":"전체 Loadbalacer 현황","type":"row"},{"datasource":"prometheus","fieldConfig":{"defaults":{"color":{"mode":"thresholds"},"mappings":[],"thresholds":{"mode":"absolute","steps":[{"color":"green","value":null},{"color":"yellow","value":5},{"color":"red","value":10}]},"unit":"short"},"overrides":[]},"gridPos":{"h":3,"w":5,"x":0,"y":1},"id":2,"options":{"colorMode":"value","graphMode":"area","justifyMode":"auto","orientation":"auto","reduceOptions":{"calcs":["lastNotNull"],"fields":"","values":false},"text":{"titleSize":20,"valueSize":48},"textMode":"auto"},"pluginVersion":"11.4.0","targets":[{"datasource":"prometheus","expr":"ktcloud_lb_total_count{job=\"ktcloud-lb\"}","interval":"","legendFormat":"","refId":"A"}],"title":"총 LB 수","type":"stat"},{"datasource":"prometheus","fieldConfig":{"defaults":{"color":{"mode":"thresholds"},"mappings":[],"thresholds":{"mode":"absolute","steps":[{"color":"red","value":null},{"color":"yellow","value":1},{"color":"green","value":2}]},"unit":"short"},"overrides":[]},"gridPos":{"h":3,"w":2,"x":5,"y":1},"id":3,"options":{"colorMode":"value","graphMode":"area","justifyMode":"auto","orientation":"auto","reduceOptions":{"calcs":["lastNotNull"],"fields":"","values":false},"text":{},"textMode":"auto"},"pluginVersion":"11.4.0","targets":[{"datasource":"prometheus","expr":"sum(ktcloud_lb_info{job=\"ktcloud-lb\"})","interval":"","legendFormat":"","refId":"A"}],"title":"정상 LB 수","type":"stat"},{"datasource":"prometheus","fieldConfig":{"defaults":{"color":{"mode":"thresholds"},"mappings":[],"thresholds":{"mode":"absolute","steps":[{"color":"green","value":null},{"color":"yellow","value":1},{"color":"red","value":2}]},"unit":"short"},"overrides":[]},"gridPos":{"h":3,"w":2,"x":7,"y":1},"id":4,"options":{"colorMode":"value","graphMode":"area","justifyMode":"auto","orientation":"auto","reduceOptions":{"calcs":["lastNotNull"],"fields":"","values":false},"text":{},"textMode":"auto"},"pluginVersion":"11.4.0","targets":[{"datasource":"prometheus","expr":"count(ktcloud_lb_info{job=\"ktcloud-lb\"} == 0)","interval":"","legendFormat":"","refId":"A"}],"title":"다운 LB 수","type":"stat"},{"datasource":"prometheus","fieldConfig":{"defaults":{"color":{"mode":"palette-classic"},"custom":{"hideFrom":{"legend":false,"tooltip":false,"vis":false}},"mappings":[]},"overrides":[]},"gridPos":{"h":3,"w":5,"x":9,"y":1},"id":5,"options":{"legend":{"displayMode":"list","placement":"right","values":["value"]},"pieType":"pie","reduceOptions":{"calcs":["lastNotNull"],"fields":"","values":false},"tooltip":{"mode":"single","sort":"none"}},"targets":[{"datasource":"prometheus","expr":"ktcloud_lb_service_type_count{job=\"ktcloud-lb\"}","interval":"","legendFormat":"{{service_type}}","refId":"A"}],"title":"서비스 타입별 로드밸런서","type":"piechart"},{"datasource":"prometheus","fieldConfig":{"defaults":{"color":{"mode":"palette-classic"},"custom":{"axisLabel":"","axisPlacement":"auto","barAlignment":0,"drawStyle":"line","fillOpacity":10,"gradientMode":"none","hideFrom":{"legend":false,"tooltip":false,"vis":false},"lineInterpolation":"linear","lineWidth":2,"pointSize":5,"scaleDistribution":{"type":"linear"},"showPoints":"never","spanNulls":false,"stacking":{"group":"A","mode":"none"},"thresholdsStyle":{"mode":"off"}},"mappings":[],"thresholds":{"mode":"absolute","steps":[{"color":"green","value":null}]},"unit":"short"},"overrides":[]},"gridPos":{"h":11,"w":10,"x":14,"y":1},"id":6,"options":{"cursor":{"sync":"crosshair"},"legend":{"calcs":[],"displayMode":"list","placement":"bottom"},"tooltip":{"mode":"multi","sort":"desc"}},"targets":[{"datasource":"prometheus","expr":"ktcloud_lb_server_count{job=\"ktcloud-lb\",lb_name=~\"$lb_name\"}","interval":"","legendFormat":"{{lb_name}} - 연결된 서버 수","refId":"A"}],"title":"Load Balancer별 연결된 서버 수","type":"timeseries"},{"datasource":"prometheus","fieldConfig":{"defaults":{"color":{"mode":"thresholds"},"custom":{"align":"center","displayMode":"auto","filterable":true,"inspect":false},"mappings":[{"options":{"0":{"color":"#F2495C","text":"DOWN"},"1":{"color":"#73BF69","text":"UP"}},"type":"value"}],"thresholds":{"mode":"absolute","steps":[{"color":"green","value":null}]}},"overrides":[{"matcher":{"id":"byName","options":"lb_name"},"properties":[{"id":"displayName","value":"LB 이름"},{"id":"custom.width","value":200}]},{"matcher":{"id":"byName","options":"상태"},"properties":[{"id":"custom.width","value":80},{"id":"custom.displayMode","value":"color-text"},{"id":"custom.cellOptions","value":{"type":"color-text"}}]},{"matcher":{"id":"byName","options":"service_ip"},"properties":[{"id":"displayName","value":"LB IP"},{"id":"custom.width","value":140}]},{"matcher":{"id":"byName","options":"service_port"},"properties":[{"id":"displayName","value":"서비스 포트"},{"id":"custom.width","value":100}]},{"matcher":{"id":"byName","options":"service_type"},"properties":[{"id":"displayName","value":"서비스 타입"},{"id":"custom.width","value":100}]},{"matcher":{"id":"byName","options":"lb_option"},"properties":[{"id":"displayName","value":"LB 옵션"},{"id":"custom.width","value":200}]},{"matcher":{"id":"byName","options":"healthcheck_type"},"properties":[{"id":"displayName","value":"헬스체크"},{"id":"custom.width","value":110}]}]},"gridPos":{"h":8,"w":14,"x":0,"y":4},"id":7,"options":{"footer":{"countRows":false,"enablePagination":true,"fields":"","reducer":[],"show":false},"showHeader":true,"sortBy":[{"desc":false,"displayName":"상태"}]},"pluginVersion":"11.4.0","targets":[{"datasource":"prometheus","expr":"ktcloud_lb_info{job=\"ktcloud-lb\"}","format":"table","instant":true,"interval":"","legendFormat":"","refId":"A"}],"title":"Load Balancer 현황","transformations":[{"id":"organize","options":{"excludeByName":{"Time":true,"__name__":true,"environment":true,"established_connections":true,"instance":true,"job":true,"lb_id":true,"service":true,"zone":true},"indexByName":{"Value":1,"healthcheck_type":6,"lb_name":0,"lb_option":5,"service_ip":2,"service_port":3,"service_type":4},"renameByName":{"Value":"상태"}}}],"type":"table"},{"collapsed":false,"gridPos":{"h":1,"w":24,"x":0,"y":12},"id":10,"panels":[],"title":"Server in LB","type":"row"},{"datasource":"prometheus","fieldConfig":{"defaults":{"color":{"mode":"thresholds"},"custom":{"align":"center","displayMode":"auto","filterable":true,"inspect":false},"mappings":[{"options":{"0":{"color":"#F2495C","text":"DOWN"},"1":{"color":"#73BF69","text":"UP"}},"type":"value"}],"thresholds":{"mode":"absolute","steps":[{"color":"green","value":null}]}},"overrides":[{"matcher":{"id":"byName","options":"lb_name"},"properties":[{"id":"displayName","value":"LB 이름"},{"id":"custom.width","value":180}]},{"matcher":{"id":"byName","options":"server_ip"},"properties":[{"id":"displayName","value":"서버 IP"},{"id":"custom.width","value":140}]},{"matcher":{"id":"byName","options":"server_port"},"properties":[{"id":"displayName","value":"서버 포트"},{"id":"custom.width","value":100}]},{"matcher":{"id":"byName","options":"Value"},"properties":[{"id":"displayName","value":"서버 상태"},{"id":"custom.width","value":100},{"id":"custom.displayMode","value":"color-background"},{"id":"custom.cellOptions","value":{"type":"color-text"}}]}]},"gridPos":{"h":10,"w":8,"x":0,"y":13},"id":11,"options":{"footer":{"countRows":false,"enablePagination":true,"fields":"","show":false},"showHeader":true,"sortBy":[{"desc":false,"displayName":"서버 상태"}]},"pluginVersion":"11.4.0","targets":[{"datasource":"prometheus","expr":"ktcloud_lb_server_state{job=\"ktcloud-lb\",lb_name=\"$selected_lb\"}","format":"table","instant":true,"interval":"","legendFormat":"","refId":"A"}],"title":"🔽 Load Balancer 선택: $selected_lb | 연결된 서버 상태","transformations":[{"id":"organize","options":{"excludeByName":{"Time":true,"__name__":true,"environment":true,"instance":true,"job":true,"lb_id":true,"service":true,"vm_id":true,"vm_name":true,"zone":true},"indexByName":{"Value":3,"lb_name":0,"server_ip":1,"server_port":2},"renameByName":{}}}],"type":"table"},{"datasource":"prometheus","description":"서버별 평균 응답 시간을 모니터링합니다.","fieldConfig":{"defaults":{"color":{"mode":"palette-classic"},"custom":{"axisLabel":"Response Time (ms)","axisPlacement":"auto","barAlignment":0,"drawStyle":"line","fillOpacity":10,"gradientMode":"none","hideFrom":{"legend":false,"tooltip":false,"vis":false},"lineInterpolation":"linear","lineWidth":2,"pointSize":5,"scaleDistribution":{"type":"linear"},"showPoints":"auto","spanNulls":false,"stacking":{"group":"A","mode":"none"},"thresholdsStyle":{"mode":"off"}},"mappings":[],"min":0,"thresholds":{"mode":"absolute","steps":[{"color":"green","value":null}]},"unit":"ms"},"overrides":[]},"gridPos":{"h":10,"w":4,"x":8,"y":13},"id":21,"options":{"cursor":{"sync":"crosshair"},"legend":{"calcs":["lastNotNull","max","mean"],"displayMode":"table","placement":"bottom","showLegend":true},"tooltip":{"mode":"multi","shred":true,"sort":"none"}},"targets":[{"datasource":"prometheus","expr":"ktcloud_server_avg_ttfb_ms{job=\"ktcloud-lb\",lb_name=\"$selected_lb\"}","interval":"","legendFormat":"{{server_ip}}:{{server_port}} (TTFB)","refId":"A"}],"title":"TTFB (Time To First Byte)","type":"timeseries"},{"datasource":"prometheus","description":"서버별 네트워크 처리량","fieldConfig":{"defaults":{"color":{"mode":"palette-classic"},"custom":{"axisLabel":"Throughput","axisPlacement":"auto","barAlignment":0,"drawStyle":"line","fillOpacity":10,"gradientMode":"none","hideFrom":{"legend":false,"tooltip":false,"vis":false},"lineInterpolation":"linear","lineWidth":2,"pointSize":5,"scaleDistribution":{"type":"linear"},"showPoints":"auto","spanNulls":false,"stacking":{"group":"A","mode":"none"},"thresholdsStyle":{"mode":"off"}},"mappings":[],"min":0,"thresholds":{"mode":"absolute","steps":[{"color":"green","value":null}]},"unit":"KBs"},"overrides":[]},"gridPos":{"h":10,"w":4,"x":12,"y":13},"id":22,"options":{"cursor":{"sync":"crosshair"},"legend":{"calcs":["lastNotNull"],"displayMode":"list","placement":"bottom","showLegend":true},"tooltip":{"mode":"multi","sort":"desc"}},"targets":[{"datasource":"prometheus","expr":"ktcloud_server_throughput_rate_kbps{job=\"ktcloud-lb\",lb_name=\"$selected_lb\"}","interval":"","legendFormat":"{{server_ip}}:{{server_port}}","refId":"A"}],"title":"Throughput","type":"timeseries"},{"datasource":"prometheus","description":"서버별 초당 요청 처리량","fieldConfig":{"defaults":{"color":{"mode":"palette-classic"},"custom":{"axisLabel":"Requests/sec","axisPlacement":"auto","barAlignment":0,"drawStyle":"line","fillOpacity":10,"gradientMode":"none","hideFrom":{"legend":false,"tooltip":false,"vis":false},"lineInterpolation":"linear","lineWidth":2,"pointSize":5,"scaleDistribution":{"type":"linear"},"showPoints":"auto","spanNulls":false,"stacking":{"group":"A","mode":"none"},"thresholdsStyle":{"mode":"off"}},"mappings":[],"min":0,"thresholds":{"mode":"absolute","steps":[{"color":"green","value":null}]},"unit":"reqps"},"overrides":[]},"gridPos":{"h":10,"w":4,"x":16,"y":13},"id":23,"options":{"cursor":{"sync":"crosshair"},"legend":{"calcs":["lastNotNull"],"displayMode":"list","placement":"bottom","showLegend":true},"tooltip":{"mode":"multi","sort":"desc"}},"targets":[{"datasource":"prometheus","expr":"ktcloud_server_requests_rate_per_sec{job=\"ktcloud-lb\",lb_name=\"$selected_lb\"}","interval":"","legendFormat":"{{server_ip}}:{{server_port}}","refId":"A"}],"title":"Requests","type":"timeseries"},{"datasource":"prometheus","description":"서버별 현재 활성 연결 수를 모니터링합니다.","fieldConfig":{"defaults":{"color":{"mode":"palette-classic"},"custom":{"axisLabel":"Active Connections","axisPlacement":"auto","barAlignment":0,"drawStyle":"line","fillOpacity":20,"gradientMode":"opacity","hideFrom":{"legend":false,"tooltip":false,"vis":false},"lineInterpolation":"linear","lineWidth":2,"pointSize":5,"scaleDistribution":{"type":"linear"},"showPoints":"auto","spanNulls":false,"stacking":{"group":"A","mode":"none"},"thresholdsStyle":{"mode":"line"}},"mappings":[],"min":0,"thresholds":{"mode":"absolute","steps":[{"color":"green","value":null},{"color":"yellow","value":50},{"color":"red","value":100}]},"unit":"short"},"overrides":[{"matcher":{"id":"byName","options":"Total"},"properties":[{"id":"color","value":{"fixedColor":"purple","mode":"fixed"}},{"id":"custom.lineWidth","value":3}]}]},"gridPos":{"h":10,"w":4,"x":20,"y":13},"id":24,"options":{"legend":{"calcs":["lastNotNull","max","mean"],"displayMode":"table","placement":"bottom","showLegend":true},"tooltip":{"mode":"multi","sort":"desc"}},"targets":[{"datasource":"prometheus","expr":"ktcloud_server_current_connections{job=\"ktcloud-lb\",lb_name=\"$selected_lb\"} \u003e 0","interval":"","legendFormat":"{{server_ip}}:{{server_port}}","refId":"A"},{"datasource":"prometheus","expr":"sum(ktcloud_server_current_connections{job=\"ktcloud-lb\",lb_name=\"$selected_lb\"} \u003e 0)","interval":"","legendFormat":"Total","refId":"B"}],"title":"Connections","type":"timeseries"}],"refresh":"30s","schemaVersion":40,"style":"dark","tags":["ktcloud","loadbalancer","monitoring"],"templating":{"list":[{"allValue":".*","datasource":{"type":"prometheus","uid":"prometheus"},"definition":"label_values(ktcloud_lb_info{job=\"ktcloud-lb\"}, lb_name)","hide":0,"includeAll":true,"label":"Load Balancer","multi":true,"name":"lb_name","query":{"query":"label_values(ktcloud_lb_info{job=\"ktcloud-lb\"}, lb_name)","refId":"PrometheusVariableQueryEditor-VariableQuery"},"refresh":1,"regex":"","sort":1,"type":"query"},{"current":{"selected":false,"text":"All","value":"$__all"},"datasource":{"type":"prometheus","uid":"prometheus"},"definition":"label_values(ktcloud_lb_info{job=\"ktcloud-lb\"}, lb_name)","hide":0,"includeAll":false,"label":"상세 조회 LB (선택)","multi":false,"name":"selected_lb","query":{"query":"label_values(ktcloud_lb_info{job=\"ktcloud-lb\"}, lb_name)","refId":"PrometheusVariableQueryEditor-VariableQuery"},"refresh":1,"regex":"","sort":1,"type":"query"},{"allValue":".*","datasource":{"type":"prometheus","uid":"prometheus"},"definition":"label_values(ktcloud_lb_info, zone)","hide":0,"includeAll":true,"label":"Zone","multi":true,"name":"zone","query":{"query":"label_values(ktcloud_lb_info, zone)","refId":"PrometheusVariableQueryEditor-VariableQuery"},"refresh":1,"regex":"","sort":1,"type":"query"}]},"time":{"from":"now-1h","to":"now"},"timepicker":{},"timezone":"Asia/Seoul","title":"KT Cloud LB Dashboard - ktcloud_test (DX-M1)","uid":"ktcloud-lb-account1-complete","version":1,"weekStart":""}}